mara_storage/__init__.py
mara_storage/azure.py
mara_storage/cli.py
mara_storage/client.py
mara_storage/compression.py
mara_storage/config.py
mara_storage/google_cloud_storage.py
mara_storage/info.py
mara_storage/local_storage.py
mara_storage/manage.py
mara_storage/sftp.py
mara_storage/shell.py
mara_storage/storages.py
mara_storage-1.1.1.dist-info/LICENSE
mara_storage-1.1.1.dist-info/METADATA
mara_storage-1.1.1.dist-info/WHEEL
mara_storage-1.1.1.dist-info/top_level.txt
mara_storage-1.1.1.dist-info/RECORD
