Metadata-Version: 2.1
Name: mara-storage
Version: 1.1.1
Summary: Configuration of storage connections for mara
Home-page: https://github.com/mara/mara-storage
Author: Mara contributors
License: MIT
Project-URL: Source Code, https://github.com/mara/mara-storage
Classifier: Development Status :: 3 - Alpha
Classifier: License :: OSI Approved :: MIT License
Classifier: Intended Audience :: Developers
Classifier: Programming Language :: Python :: 3.6
Classifier: Programming Language :: Python :: 3.7
Classifier: Programming Language :: Python :: 3.8
Classifier: Programming Language :: Python :: 3.9
Classifier: Programming Language :: Python :: 3.10
Requires-Python: >=3.6
License-File: LICENSE
Requires-Dist: click
Provides-Extra: azure-blob
Requires-Dist: azure-storage-blob ; extra == 'azure-blob'
Provides-Extra: google-cloud-storage
Requires-Dist: google-cloud-storage ; extra == 'google-cloud-storage'
Requires-Dist: google-oauth ; extra == 'google-cloud-storage'
Provides-Extra: sftp
Requires-Dist: pysftp ; extra == 'sftp'
Provides-Extra: test
Requires-Dist: pytest ; extra == 'test'
